pinline/__init__.py
pinline/inliner.py
pinline-0.1.1.dist-info/LICENSE
pinline-0.1.1.dist-info/METADATA
pinline-0.1.1.dist-info/WHEEL
pinline-0.1.1.dist-info/top_level.txt
pinline-0.1.1.dist-info/RECORD
