Metadata-Version: 2.1
Name: pinline
Version: 0.1.1
Summary: UNKNOWN
Home-page: UNKNOWN
Author: Simon Perkins
Author-email: simon.perkins@gmail.com
License: UNKNOWN
Platform: UNKNOWN
Requires-Python: ==3.*,>=3.6.0
Requires-Dist: unparse (==0.*,>=0.2.0)
Provides-Extra: dev
Requires-Dist: bump2version (==1.*,>=1.0.0) ; extra == 'dev'
Provides-Extra: testing
Requires-Dist: astunparse (==1.*,>=1.6.3) ; extra == 'testing'
Requires-Dist: pytest (==5.*,>=5.2.0,>=5.4.2) ; extra == 'testing'
Requires-Dist: pytest-flake8 (==1.*,>=1.0.6) ; extra == 'testing'
